conf_master/__init__.py
conf_master/conf_master.py
conf_master/exceptions.py
conf_master/loaders.py
conf_master/savers.py
conf_master/validators.py
conf_master-2.0.0.dist-info/LICENSE.txt
conf_master-2.0.0.dist-info/METADATA
conf_master-2.0.0.dist-info/WHEEL
conf_master-2.0.0.dist-info/RECORD
