Metadata-Version: 2.1
Name: conf-master
Version: 2.0.0
Summary: 
License: MIT
Author: alvaroroco
Author-email: alvaroroco@gmail.com
Requires-Python: >=3.8
Classifier: Development Status :: 4 - Beta
Classifier: License :: OSI Approved :: MIT License
Classifier: Programming Language :: Python
Classifier: Programming Language :: Python :: 3
Classifier: Programming Language :: Python :: 3.8
Classifier: Programming Language :: Python :: 3.9
Classifier: Programming Language :: Python :: 3.10
Classifier: Programming Language :: Python :: 3.11
Classifier: Programming Language :: Python :: 3.12
Classifier: Programming Language :: Python :: Implementation :: CPython
Classifier: Programming Language :: Python :: Implementation :: PyPy
Project-URL: documentation, https://github.com/alvaroroco/conf-master#readme
Project-URL: issues, https://github.com/alvaroroco/conf-master/issues
Project-URL: source, https://github.com/alvaroroco/conf-master
